{
    "swagger": "2.0",
    "info": {
      "version": "1.0.0",
      "title": "AgroBot",
      "description": "AgroBot."
    },
    "host": "localhost:3000",
    "basePath": "/",
    "tags": [],
    "schemes": [
      "http",
      "https"
    ],
    "securityDefinitions": {
      "Bearer": {
        "name": "Authorization",
        "in": "headers",
        "type": "apiKey",
        "description": "authorization token"
      }
    },
    "consumes": [
      "application/json"
    ],
    "produces": [
      "application/json"
    ],

    "definitions": {}
  }